torchpaqm/__init__.py
torchpaqm/loudness.py
torchpaqm/masker.py
torchpaqm/paqm.py
torchpaqm/spectrum.py
torchpaqm/transfer.py
torchpaqm/utils/__init__.py
torchpaqm/utils/dataset.py
torchpaqm/utils/general.py
torchpaqm-0.0.1.dist-info/licenses/LICENSE
torchpaqm-0.0.1.dist-info/METADATA
torchpaqm-0.0.1.dist-info/WHEEL
torchpaqm-0.0.1.dist-info/top_level.txt
torchpaqm-0.0.1.dist-info/RECORD
