Metadata-Version: 2.4
Name: torchpaqm
Version: 0.0.1
Summary: Implementation of PAQM in Python using pytorch for vectorized operations.
Author-email: Bernardo Vieira de Miranda <bvm810@gmail.com>
Project-URL: Homepage, https://github.com/bvm810/torchpaqm
Project-URL: Issues, https://github.com/bvm810/torchpaqm/issues
Classifier: Programming Language :: Python :: 3
Classifier: Operating System :: OS Independent
Classifier: License :: OSI Approved :: MIT License
Classifier: Environment :: GPU :: NVIDIA CUDA
Classifier: Framework :: Pytest
Requires-Python: >=3.10.8
License-File: LICENSE
Requires-Dist: torch>=2.2.0
Requires-Dist: torchaudio>=2.2.0
Requires-Dist: scipy>=1.15.2
Provides-Extra: tests
Requires-Dist: pytest>=8.3.5; extra == "tests"
Requires-Dist: matplotlib>=3.10.1; extra == "tests"
Dynamic: license-file
